Metadata-Version: 2.1
Name: ron2dec
Version: 1.0.2
Summary: Convert Roman numerals to decimals.
Author-email: romanhaziahmetov3@gmail.com
